[
  {
    "name": "Maxx C",
    "image": "images/cropped/Maxx C.jpg"
  },
  {
    "name": "Exodia the Forbidden One",
    "image": "images/cropped/Exodia the Forbidden One.jpg"
  },
  {
    "name": "The Humble Sentry",
    "image": "images/cropped/The Humble Sentry.jpg"
  },
  {
    "name": "Pot of Avarice",
    "image": "images/cropped/Pot of Avarice.jpg"
  },
  {
    "name": "Kuriboh",
    "image": "images/cropped/Kuriboh.jpg"
  },
  {
    "name": "Dark Gray",
    "image": "images/cropped/Dark Gray.jpg"
  },
  {
    "name": "Symbol of Friendship",
    "image": "images/cropped/Symbol of Friendship.jpg"
  },
  {
    "name": "Tatsunootoshigo",
    "image": "images/cropped/Tatsunootoshigo.jpg"
  },
  {
    "name": "Magic Cylinder",
    "image": "images/cropped/Magic Cylinder.jpg"
  },
  {
    "name": "Genetic Woman",
    "image": "images/cropped/Genetic Woman.jpg"
  },
  {
    "name": "Overworked",
    "image": "images/cropped/Overworked.jpg"
  },
  {
    "name": "Polymerization",
    "image": "images/cropped/Polymerization.jpg"
  },
  {
    "name": "Black Luster Soldier",
    "image": "images/cropped/Black Luster Soldier.jpg"
  },
  {
    "name": "Dark Magician Girl",
    "image": "images/cropped/Dark Magician Girl.jpg"
  },
  {
    "name": "Humpty Grumpty",
    "image": "images/cropped/Humpty Grumpty.jpg"
  },
  {
    "name": "Toadally Awesome",
    "image": "images/cropped/Toadally Awesome.jpg"
  },
  {
    "name": "Hungry Burger",
    "image": "images/cropped/Hungry Burger.jpg"
  },
  {
    "name": "People Running About",
    "image": "images/cropped/People Running About.jpg"
  },
  {
    "name": "Pot of Duality",
    "image": "images/cropped/Pot of Duality.jpg"
  },
  {
    "name": "D-Boyz",
    "image": "images/cropped/D-Boyz.jpg"
  },
  {
    "name": "Mirror Force",
    "image": "images/cropped/Mirror Force.jpg"
  },
  {
    "name": "Slifer The Sky Dragon",
    "image": "images/cropped/Slifer The Sky Dragon.jpg"
  },
  {
    "name": "Gift Card",
    "image": "images/cropped/Gift Card.jpg"
  },
  {
    "name": "Pot of Greed",
    "image": "images/cropped/Pot of Greed.jpg"
  },
  {
    "name": "Dr. Frankenderp",
    "image": "images/cropped/Dr. Frankenderp.jpg"
  },
  {
    "name": "Great Long Nose",
    "image": "images/cropped/Great Long Nose.jpg"
  },
  {
    "name": "Tardy Orc",
    "image": "images/cropped/Tardy Orc.jpg"
  },
  {
    "name": "Santa Claws",
    "image": "images/cropped/Santa Claws.jpg"
  },
 
  {
    "name": "Monster Reborn",
    "image": "images/cropped/Monster Reborn.jpg"
  },
  {
    "name": "Foolish Revival",
    "image": "images/cropped/Foolish Revival.jpg"
  },
  {
    "name": "Cold Feet",
    "image": "images/cropped/Cold Feet.jpg"
  },
  {
    "name": "Flelf",
    "image": "images/cropped/Flelf.jpg"
  },
  {
    "name": "Pot Of Generosity",
    "image": "images/cropped/Pot Of Generosity.jpg"
  },
  {
    "name": "Doom Donuts",
    "image": "images/cropped/Doom Donuts.jpg"
  },
  {
    "name": "Ojama Yellow",
    "image": "images/cropped/Ojama Yellow.jpg"
  }
]